asdil/__init__.py
asdil/code.py
asdil/fo.py
asdil/log.py
asdil/mail.py
asdil/mysql.py
asdil/ssh.py
asdil/tab.py
asdil/tool.py
asdil-1.7.4.2.dist-info/entry_points.txt
asdil-1.7.4.2.dist-info/WHEEL
asdil-1.7.4.2.dist-info/METADATA
asdil-1.7.4.2.dist-info/RECORD
